ccodegen/__init__.py
ccodegen/ccodegen.py
tests/__init__.py
tests/test.py
ccodegen-0.1.1.dist-info/LICENSE
ccodegen-0.1.1.dist-info/METADATA
ccodegen-0.1.1.dist-info/WHEEL
ccodegen-0.1.1.dist-info/top_level.txt
ccodegen-0.1.1.dist-info/RECORD
